{
  "choices": [
    {
      "id": "612b5c40-3872-41aa-927b-864c4c5906b5",
      "name": "Add journal entry",
      "type": "Capture",
      "command": false,
      "appendLink": false,
      "captureTo": "bins/daily/{{DATE:gggg-MM-DD - ddd MMM D}}.md",
      "captureToActiveFile": false,
      "createFileIfItDoesntExist": {
        "enabled": true,
        "createWithTemplate": false,
        "template": ""
      },
      "format": {
        "enabled": true,
        "format": "- {{DATE:HH:mm}} {{VALUE}}\\n"
      },
      "insertAfter": {
        "enabled": false,
        "after": "## What did I do today",
        "insertAtEnd": false,
        "createIfNotFound": false,
        "createIfNotFoundLocation": "top"
      },
      "prepend": false,
      "task": false,
      "openFileInNewTab": {
        "enabled": false,
        "direction": "vertical",
        "focus": true
      },
      "openFile": false,
      "openFileInMode": "default"
    },
    {
      "id": "37d67772-c5c0-423b-8ad2-c84e530b12de",
      "name": "Customers",
      "type": "Template",
      "command": false,
      "templatePath": "",
      "fileNameFormat": {
        "enabled": false,
        "format": ""
      },
      "folder": {
        "enabled": false,
        "folders": [],
        "chooseWhenCreatingNote": false,
        "createInSameFolderAsActiveFile": false,
        "chooseFromSubfolders": false
      },
      "appendLink": false,
      "openFileInNewTab": {
        "enabled": false,
        "direction": "vertical",
        "focus": true
      },
      "openFile": false,
      "openFileInMode": "default",
      "setFileExistsBehavior": true,
      "fileExistsMode": "Increment the file name"
    }
  ],
  "macros": [],
  "inputPrompt": "single-line",
  "devMode": false,
  "templateFolderPath": "Templates/ObsidianTemplate",
  "announceUpdates": true,
  "version": "0.23.0",
  "ai": {
    "OpenAIApiKey": "",
    "defaultModel": "Ask me",
    "defaultSystemPrompt": "As an AI assistant within Obsidian, your primary goal is to help users manage their ideas and knowledge more effectively. Format your responses using Markdown syntax. Please use the [[Obsidian]] link format. You can write aliases for the links by writing [[Obsidian|the alias after the pipe symbol]]. To use mathematical notation, use LaTeX syntax. LaTeX syntax for larger equations should be on separate lines, surrounded with double dollar signs ($$). You can also inline math expressions by wrapping it in $ symbols. For example, use $$w_{ij}^{\text{new}}:=w_{ij}^{\text{current}}+etacdotdelta_jcdot x_{ij}$$ on a separate line, but you can write \"($eta$ = learning rate, $delta_j$ = error term, $x_{ij}$ = input)\" inline.",
    "promptTemplatesFolderPath": "",
    "showAssistant": true
  },
  "migrations": {
    "migrateToMacroIDFromEmbeddedMacro": true,
    "useQuickAddTemplateFolder": true,
    "incrementFileNameSettingMoveToDefaultBehavior": true,
    "mutualExclusionInsertAfterAndWriteToBottomOfFile": true,
    "setVersionAfterUpdateModalRelease": true
  }
}